[
  {
    "id": "_5iuekwtep",
    "userId": "_aqu2uicg8",
    "email": "demo@gmail.com",
    "name": "DEMO",
    "companyName": "d2webtech",
    "companyEmail": "d2webtech@gnmail.com",
    "companyAddress": "home",
    "gstNumber": "123456"
  },
  {
    "id": "_z61ak0nu9",
    "userId": "_aqu2uicg8",
    "email": "demo2@gmail.com",
    "name": "jenish",
    "companyName": "d2webtech",
    "companyEmail": "d2webtech@gnmail.com",
    "companyAddress": "home",
    "gstNumber": "123456"
  },
  {
    "id": "_n1k5dg3bu",
    "userId": "_aqu2uicg8",
    "email": "demo2@gmail.com",
    "name": "rahul",
    "companyName": "d2webtech",
    "companyEmail": "d2webtech@gmail.com",
    "companyAddress": "home",
    "gstNumber": "789123"
  },
  {
    "id": "_kkb0z5stt",
    "userId": "_aqu2uicg8",
    "email": "fake_user5@officehourtesting.com",
    "name": "umesh",
    "companyName": "d2webtech",
    "companyEmail": "d2webtech@gmail.com",
    "companyAddress": "home",
    "gstNumber": "789456"
  },
  {
    "id": "_8njce4xei",
    "userId": "_aqu2uicg8",
    "email": "rahafa5485@cutxsew.com",
    "name": "jeet",
    "companyName": "d2webtech",
    "companyEmail": "d2webtech@gmail.com",
    "companyAddress": "home",
    "gstNumber": "456789"
  },
  {
    "id": "_44q9mwldz",
    "userId": "_ys2x6es39",
    "email": "chiragdevaliya@gmail.com",
    "name": "chirag",
    "companyName": "d2webtech",
    "companyEmail": "d2webtech@gmail.com",
    "companyAddress": "home",
    "gstNumber": "789123"
  },
  {
    "id": "_tj2eoojon",
    "userId": "_ys2x6es39",
    "email": "demo@gmail.com",
    "name": "jenish",
    "companyName": "d2webtech",
    "companyEmail": "d2webtech@gmail.com",
    "companyAddress": "home",
    "gstNumber": "789456"
  },
  {
    "id": "_nb3zckkbz",
    "userId": "_ys2x6es39",
    "email": "chiragdevaliya@gmail.com",
    "name": "DEMO",
    "companyName": "d2webtech",
    "companyEmail": "d2webtech@gnmail.com",
    "companyAddress": "home",
    "gstNumber": "123456"
  },
  {
    "id": "_atep3nkwg",
    "userId": "_ys2x6es39",
    "email": "demo@gmail.com",
    "name": "ayush",
    "companyName": "d2webtech",
    "companyEmail": "d2webtech@gmail.com",
    "companyAddress": "home",
    "gstNumber": "456789"
  },
  {
    "id": "_vh3cg0lrd",
    "userId": "_ys2x6es39",
    "email": "jaxirin692@reebsd.com",
    "name": "UMESH",
    "companyName": "d2webtech",
    "companyEmail": "d2webtech@gmail.com",
    "companyAddress": "home",
    "gstNumber": "456789"
  },
  {
    "id": "_abcb66i2a",
    "userId": "_ys2x6es39",
    "email": "demo2@gmail.com",
    "name": "Chirag Devaliya",
    "companyName": "d2webtech",
    "companyEmail": "d2webtech@gmail.com",
    "companyAddress": "home",
    "gstNumber": "789123"
  },
  {
    "id": "_a9kulkb62",
    "userId": "_ys2x6es39",
    "email": "rahafa5485@cutxsew.com",
    "name": "ayush",
    "companyName": "d2webtech",
    "companyEmail": "d2webtech@gmail.com",
    "companyAddress": "home",
    "gstNumber": "789123"
  }
]